{
    "version": 1,
    "size": {
        "x": 32,
        "y": 32
    },
    "license": "CC-BY-SA-3.0",
    "copyright": "Taken from https://github.com/discordia-space/CEV-Eris/blob/01f7518e0f8177734a6579aba2bbf76024aa96c40/icons/obj/recycling.dmi, Modified by AssignedGod for Aurora Song",
    "states": [
        {
            "name": "grinder-b0"

        },
        {
            "name": "grinder-b1",
            "delays": [
                [
                    0.1,
                    0.1,
                    0.1,
                    0.1,
                    0.1,
                    0.1
                ]
            ]
        }
    ]
}
